{
  "created_at": "2026-02-23T14:35:04Z",
  "default_branch": "main",
  "snapshots": [
    {
      "archived": false,
      "last_commit_at": "2026-06-04T16:30:08Z",
      "latest_release": null,
      "license_spdx": "MIT",
      "refreshed_at": "2026-06-14T01:51:22Z",
      "stars": 16056
    },
    {
      "archived": false,
      "last_commit_at": "2026-06-22T11:24:17Z",
      "latest_release": null,
      "license_spdx": "MIT",
      "refreshed_at": "2026-06-29T11:26:23Z",
      "stars": 16128
    }
  ]
}
